infixed.py
infixed-1.1.0.dist-info/LICENSE
infixed-1.1.0.dist-info/WHEEL
infixed-1.1.0.dist-info/METADATA
infixed-1.1.0.dist-info/RECORD
