Metadata-Version: 2.1
Name: infixed
Version: 1.1.0
Summary: Provides `make_infix` to create custom infix operators and multiple premade infix operators.
Home-page: https://github.com/techieji/infixed
License: UNKNOWN
Author: Pradhyum R
Author-email: drpradhyum2016@outlook.com
Requires-Python: >=3.8
Classifier: License :: OSI Approved :: MIT License
